vimix
