Metadata-Version: 1.1
Name: vimix
Version: 0.0.2
Summary: Make minimum environment for Vim script
Home-page: https://github.com/mtwtkman/vimix
Author: boku
Author-email: punipuniomochi@gmail.com
License: WTFPL
Download-URL: https://github.com/mtwtkman/vimix/tarball/master
Platform: UNKNOWN
Classifier: Development Status :: 3 - Alpha
Classifier: Programming Language :: Python :: 3
Classifier: Programming Language :: Python :: 3.4
Classifier: Topic :: Software Development
